aws_console/__init__.py
aws_console/inspect.py
aws_console/main.py
aws_console-0.3.0.dist-info/METADATA
aws_console-0.3.0.dist-info/WHEEL
aws_console-0.3.0.dist-info/entry_points.txt
aws_console-0.3.0.dist-info/top_level.txt
aws_console-0.3.0.dist-info/RECORD
