Metadata-Version: 2.1
Name: aws-console
Version: 0.3.0
Summary: a console for easily using AWS with boto3
Home-page: https://github.com/haarcuba/aws_console
Author: Yoav Kleinberger
Author-email: haarcuba@gmail.com
License: UNKNOWN
Keywords: AWS,boto,amazon
Platform: UNKNOWN
Classifier: Programming Language :: Python
Requires-Dist: ipython (>=5.2.2)
Requires-Dist: boto3
Requires-Dist: myconsole
